{
  "today": {
    "location": "Henderson",
    "date": "Thursday, May 21",
    "sunrise": "5:30 AM",
    "sunset": "7:43 PM",
    "uvIndex": 8.45,
    "day": {
      "temp": 89,
      "condition": "Clear sky",
      "humidity": 7,
      "windSpeed": 6,
      "windDir": "SE"
    },
    "night": {
      "temp": 79,
      "condition": "Clear sky",
      "humidity": 7,
      "windSpeed": 14,
      "windDir": "S"
    },
    "high": 91,
    "low": 65
  },
  "forecast": [
    {
      "dayName": "22 Fri",
      "high": 93,
      "low": 69,
      "condition": "Overcast",
      "precipChance": 2,
      "windSpeed": 20,
      "windDir": "S"
    },
    {
      "dayName": "23 Sat",
      "high": 91,
      "low": 70,
      "condition": "Clear sky",
      "precipChance": 1,
      "windSpeed": 21,
      "windDir": "S"
    },
    {
      "dayName": "24 Sun",
      "high": 92,
      "low": 72,
      "condition": "Clear sky",
      "precipChance": 0,
      "windSpeed": 20,
      "windDir": "S"
    },
    {
      "dayName": "25 Mon",
      "high": 92,
      "low": 73,
      "condition": "Clear sky",
      "precipChance": 1,
      "windSpeed": 19,
      "windDir": "S"
    },
    {
      "dayName": "26 Tue",
      "high": 89,
      "low": 69,
      "condition": "Overcast",
      "precipChance": 0,
      "windSpeed": 24,
      "windDir": "SW"
    },
    {
      "dayName": "27 Wed",
      "high": 88,
      "low": 67,
      "condition": "Overcast",
      "precipChance": 1,
      "windSpeed": 15,
      "windDir": "S"
    }
  ]
}